carrera/__init__.py
carrera/message.py
carrera/utils.py
carrera/actors/__init__.py
carrera/actors/base.py
carrera/actors/process.py
carrera/actors/thread.py
carrera/communications/__init__.py
carrera/communications/remote_actor.py
carrera/communications/workers/__init__.py
carrera/dispatcher/__init__.py
carrera/dispatcher/dispatcher_unit.py
carrera-0.0.3.dist-info/METADATA
carrera-0.0.3.dist-info/WHEEL
carrera-0.0.3.dist-info/top_level.txt
carrera-0.0.3.dist-info/RECORD
